twemoir
