Metadata-Version: 1.1
Name: django-twemoir
Version: 0.1.6
Summary: Twitter data models.
Home-page: http://github.com/fish2000/django-twemoir/
Author: Alexander Bohn
Author-email: fish2000@gmail.com
License: MIT
Download-URL: http://github.com/fish2000/django-twemoir/zipball/master
Keywords: python endjango-twemoirment variable simple template text
Platform: any
Classifier: Development Status :: 5 - Production/Stable
Classifier: License :: OSI Approved :: MIT License
Classifier: Operating System :: MacOS
Classifier: Operating System :: Microsoft :: Windows
Classifier: Operating System :: OS Independent
Classifier: Operating System :: POSIX
Classifier: Operating System :: Unix
Classifier: Programming Language :: Python :: 2.6
